[
    {
        "id": 1,
        "titulo": "HTML",
        "cor": "#e44d26",
        "logo": "/media/HTML-logo.png",
        "home": true,
        "exercicio": true
    },
    {
        "id": 2,
        "titulo": "CSS",
        "cor": "#264de4",
        "logo": "/media/CSS-logo.png",
        "home": true,
        "exercicio": true
    },
    {
        "id": 3,
        "titulo": "JavaScript",
        "cor": "#f7df1e",
        "logo": "/media/JS-logo.png",
        "home": true,
        "exercicio": true
    },
    {
        "id": 4,
        "titulo": "NodeJS",
        "cor": "#80bd41",
        "logo": "/media/Node-logo.png",
        "home": false,
        "exercicio": false
    },
    {
        "id": 5,
        "titulo": "ReactJS",
        "cor": "#53c1de",
        "logo": "/media/React-logo.png",
        "home": true,
        "exercicio": true
    },
    {
        "id": 6,
        "titulo": "JSON",
        "cor": "#727272",
        "logo": "/media/JSON-logo.png",
        "home": false,
        "exercicio": false
    },
    {
        "id": 7,
        "titulo": "Git",
        "cor": "#f05033",
        "logo": "/media/Git-logo.png",
        "home": false,
        "exercicio": false
    },
    {
        "id": 8,
        "titulo": "MySQL",
        "cor": "#4479a1",
        "logo": "/media/MySQL-logo.png",
        "home": false,
        "exercicio": false
    },
    {
        "id": 9,
        "titulo": "Visual Studio Code",
        "cor": "#1585d0",
        "logo": "/media/VSC-logo.png",
        "home": false,
        "exercicio": false
    }
]